utils_pna/__init__.py
utils_pna/areas.py
utils_pna/crs.py
utils_pna/dates.py
utils_pna/dist.py
utils_pna/geom.py
utils_pna/interpolacion.py
utils_pna/postprocess.py
utils_pna/queries.py
utils_pna/static.py
utils_pna-0.0.23.dist-info/METADATA
utils_pna-0.0.23.dist-info/WHEEL
utils_pna-0.0.23.dist-info/top_level.txt
utils_pna-0.0.23.dist-info/RECORD
